anyGPT/__init__.py
anyGPT/config/__init__.py
anyGPT/config/settings.py
anyGPT/config/util.py
anyGPT/data/__init__.py
anyGPT/data/experience_dataset.py
anyGPT/data/next_token_dataset.py
anyGPT/data/prepare_data.py
anyGPT/data/util.py
anyGPT/environments/__init__.py
anyGPT/environments/sequence_classification_env.py
anyGPT/inference/__init__.py
anyGPT/inference/run.py
anyGPT/inference/runner.py
anyGPT/models/__init__.py
anyGPT/models/anygpt.py
anyGPT/models/anygpt_critic.py
anyGPT/models/anygpt_lit.py
anyGPT/models/anygpt_ppo_lit.py
anyGPT/models/modules.py
anyGPT/models/operators.py
anyGPT/models/ppo_policy.py
anyGPT/service/__init__.py
anyGPT/service/app.py
anyGPT/training/__init__.py
anyGPT/training/model_checkpoint.py
anyGPT/training/pretrain.py
anyGPT/training/rl_train.py
anyGPT/training/trainers.py
anyGPT-0.1.0.dist-info/LICENSE
anyGPT-0.1.0.dist-info/METADATA
anyGPT-0.1.0.dist-info/WHEEL
anyGPT-0.1.0.dist-info/entry_points.txt
anyGPT-0.1.0.dist-info/top_level.txt
anyGPT-0.1.0.dist-info/RECORD
