Metadata-Version: 2.1
Name: anyGPT
Version: 0.1.0
Summary: A general purpose library for training any type of GPT model. Support for gpt-1, gpt-2, and gpt-3 models.
Author: Miguel Alonso Jr
Author-email: drmiguelalonsojr@gmail.com
Maintainer: Chad Dettmering
Maintainer-email: chad.dettmering@gmail.com
License: MIT
Keywords: ai,ml,rl,gpt,llm,rlhf
Classifier: Development Status :: 4 - Beta
Classifier: Intended Audience :: Developers
Classifier: License :: OSI Approved :: MIT License
Classifier: Programming Language :: Python :: 3.10
Classifier: Topic :: Scientific/Engineering :: Artificial Intelligence
Classifier: Typing :: Typed
License-File: LICENSE
Requires-Dist: torch (>=2.0.0)
Requires-Dist: numpy
Requires-Dist: transformers
Requires-Dist: datasets
Requires-Dist: tiktoken
Requires-Dist: wandb
Requires-Dist: tqdm
Requires-Dist: PyYAML
Requires-Dist: lightning
Requires-Dist: tensorboard
Requires-Dist: fastapi
Requires-Dist: uvicorn
Requires-Dist: gymnasium
Provides-Extra: dev
Requires-Dist: black (==23.3.0) ; extra == 'dev'
Requires-Dist: pytest ; extra == 'dev'
Requires-Dist: pytest-cov ; extra == 'dev'
Requires-Dist: pytest-sugar ; extra == 'dev'
Requires-Dist: build ; extra == 'dev'
Requires-Dist: twine ; extra == 'dev'
Requires-Dist: httpx ; extra == 'dev'
